CHANGES.rst
LICENSE
MANIFEST.in
Makefile
README.rst
requirements.txt
requirements_dev.txt
setup.cfg
setup.py
esgf_pyclient.egg-info/PKG-INFO
esgf_pyclient.egg-info/SOURCES.txt
esgf_pyclient.egg-info/dependency_links.txt
esgf_pyclient.egg-info/not-zip-safe
esgf_pyclient.egg-info/requires.txt
esgf_pyclient.egg-info/top_level.txt
pyesgf/__init__.py
pyesgf/exceptions.py
pyesgf/logon.py
pyesgf/util.py
pyesgf/search/__init__.py
pyesgf/search/connection.py
pyesgf/search/constraints.py
pyesgf/search/consts.py
pyesgf/search/context.py
pyesgf/search/exceptions.py
pyesgf/search/results.py
pyesgf/security/__init__.py
pyesgf/security/ats.py