Metadata-Version: 2.1
Name: esgf-pyclient
Version: 0.3.1
Summary: A library interacting with ESGF services within Python
Home-page: http://esgf-pyclient.readthedocs.org
Download-URL: https://github.com/ESGF/esgf-pyclient
Author: Ag Stephens
Author-email: Ag.Stephens@stfc.ac.uk
License: BSD
Platform: UNKNOWN
Classifier: Development Status :: 4 - Beta
Classifier: License :: OSI Approved :: BSD License
Classifier: Topic :: Scientific/Engineering
Classifier: Programming Language :: Python
Classifier: Programming Language :: Python :: 3
Classifier: Programming Language :: Python :: 3.6
Classifier: Programming Language :: Python :: 3.7
Classifier: Programming Language :: Python :: 3.8
Classifier: Programming Language :: Python :: 3.9
Requires-Python: >=3.6.0
Provides-Extra: dev
License-File: LICENSE
